cua_docker/__init__.py
cua_docker/computer_agent.py
cua_docker/config.py
cua_docker/cua_agent.py
cua_docker/cua_docker_actions.py
cua_docker/cua_docker_loop.py
cua_docker/cua_request.py
cua_sdk/__init__.py
cua_sdk/agent.py
cua_sdk-0.1.0.dist-info/METADATA
cua_sdk-0.1.0.dist-info/WHEEL
cua_sdk-0.1.0.dist-info/top_level.txt
cua_sdk-0.1.0.dist-info/RECORD
