Metadata-Version: 2.4
Name: cua-sdk
Version: 0.1.0
Summary: A reusable Python SDK for controlling a computer-using agent in a virtual desktop.
Home-page: https://github.com/eliastsoukatos/computer_use
Author: Elias Tsoukatos
Author-email: Elias Tsoukatos <your.email@example.com>
License: MIT
Classifier: Programming Language :: Python :: 3
Classifier: Operating System :: OS Independent
Requires-Python: >=3.8
Requires-Dist: openai
Requires-Dist: python-dotenv
Dynamic: author
Dynamic: home-page
Dynamic: requires-python
